pyxel_server/__init__.py
pyxel_server/client.py
pyxel_server/connection.py
pyxel_server/data.py
pyxel_server/pyxelobj.py
pyxel_server/server.py
pyxel_server-0.0.3.1.dist-info/LICENCE
pyxel_server-0.0.3.1.dist-info/METADATA
pyxel_server-0.0.3.1.dist-info/WHEEL
pyxel_server-0.0.3.1.dist-info/top_level.txt
pyxel_server-0.0.3.1.dist-info/RECORD
