Metadata-Version: 2.1
Name: pyxel-server
Version: 0.0.3.1
Summary: A simple to use API for integration between your Pyxel games with servers.
Home-page: https://github.com/FloppiDisk/pyxel_server
Author: Charlie Suy
Author-email: floppi.disky@gmail.com
License: UNKNOWN
Project-URL: Bug Tracker, https://github.com/FloppiDisk/pyxel_server/issues
Platform: UNKNOWN
Classifier: Programming Language :: Python :: 3
Classifier: License :: OSI Approved :: MIT License
Classifier: Operating System :: OS Independent
Requires-Python: >=3.6.8
License-File: LICENCE
